.isort.cfg
CHANGES.rst
CONTRIBUTORS.rst
MANIFEST.in
README.rst
buildout.cfg
ci.cfg
setup.py
docs/index.rst
src/collective/__init__.py
src/collective.normalize_buildout.egg-info/PKG-INFO
src/collective.normalize_buildout.egg-info/SOURCES.txt
src/collective.normalize_buildout.egg-info/dependency_links.txt
src/collective.normalize_buildout.egg-info/entry_points.txt
src/collective.normalize_buildout.egg-info/namespace_packages.txt
src/collective.normalize_buildout.egg-info/not-zip-safe
src/collective.normalize_buildout.egg-info/requires.txt
src/collective.normalize_buildout.egg-info/top_level.txt
src/collective/normalize_buildout/__init__.py
src/collective/normalize_buildout/cmd.py
src/collective/normalize_buildout/testing.py
src/collective/normalize_buildout/tests/__init__.py
src/collective/normalize_buildout/tests/test_script.py